{
  "policy_note": "Default policy is 90% line coverage per source file. Coverage runs use `--test-threads=1` (see Makefile) to serialise env-sensitive tests across lib + integration binaries. Session 6 close (2026-05-16): TOTAL 97.28%, 59/59 files at ≥90%, zero debt baselines. The static `CALL_COUNT < 3` guard in `decode/diag.rs::log_decode_entry` is exercised via `tests/test_decode_diag.rs`, a dedicated integration binary that gets a fresh process where the counter starts at 0. 2026-05-19 compute-refactor regression: branch added ~344 LOC of W10 state-bridge wrappers (`decode_token_with_state_dump_*_fn`, `coarse_*_with_state_masked`) to `decode/mod.rs` and `trait_impl/mod.rs` without proportional Metal-side test coverage. 2026-05-20 partial recovery: 4 new tests in `tests/test_metal_decode_synthetic.rs` exercise the masked-fn surface under `StateDumpMask::{Full, HOnly, None}` plus the unmasked wrapper — decode/mod.rs back to 93.36%, no longer needs a debt baseline. trait_impl/mod.rs's `hybrid_decode_attention_layer` body still uncovered: the synthetic Q4_K fixture null-ptrs deep in `decode_attention_layer` (needs a real vindex with attn_kquant data installed, not just raw Q4_K bytes). Keep its baseline at 87 and clear it when the hybrid pipeline gets a proper end-to-end synthetic vindex fixture in this crate.",
  "include_globs": [
    "crates/larql-compute-metal/src/*.rs",
    "crates/larql-compute-metal/src/**/*.rs"
  ],
  "exclude_globs": [],
  "default_line_min_percent": 90.0,
  "total_line_min_percent": 96.0,
  "per_file_line_min_percent": {
    "crates/larql-compute-metal/src/trait_impl/mod.rs": 87.0
  }
}
